tabula-1.0.6-SNAPSHOT-jar-with-dependencies.jar
tungsten/__init__.py
tungsten/globally_harmonized_system/__init__.py
tungsten/globally_harmonized_system/safety_data_sheet.py
tungsten/globally_harmonized_system/safety_data_sheet_rules.py
tungsten/parsers/__init__.py
tungsten/parsers/field_parse.py
tungsten/parsers/parsing_hierarchy.py
tungsten/parsers/sds_parser.py
tungsten/parsers/supplier/__init__.py
tungsten/parsers/supplier/sigma_aldrich/__init__.py
tungsten/parsers/supplier/sigma_aldrich/field_parse.py
tungsten/parsers/supplier/sigma_aldrich/pictogram_injector.py
tungsten/parsers/supplier/sigma_aldrich/safety_data_sheet_rules.py
tungsten/parsers/supplier/sigma_aldrich/sds_parser.py
tungsten/parsers/supplier/sigma_aldrich/table_injector.py
tungsten/pictograms/Aquatic-pollut-red.gif
tungsten/pictograms/README.md
tungsten/pictograms/acid_red.gif
tungsten/pictograms/bottle.gif
tungsten/pictograms/exclam.gif
tungsten/pictograms/explos.gif
tungsten/pictograms/flamme.gif
tungsten/pictograms/pictograms.py
tungsten/pictograms/rondflam.gif
tungsten/pictograms/silhouete.gif
tungsten/pictograms/skull.gif
tungsten_sds-0.8.0.dist-info/LICENSE
tungsten_sds-0.8.0.dist-info/METADATA
tungsten_sds-0.8.0.dist-info/WHEEL
tungsten_sds-0.8.0.dist-info/RECORD
