Metadata-Version: 2.1
Name: tungsten-sds
Version: 0.8.0
Summary: An MSDS parser.
Home-page: https://github.com/Den4200/tungsten
License: MIT
Keywords: sds,parser
Author: Dennis Pham
Author-email: dennis@dennispham.me
Requires-Python: >=3.10,<4.0
Classifier: License :: OSI Approved :: MIT License
Classifier: Programming Language :: Python :: 3
Classifier: Programming Language :: Python :: 3.10
Classifier: Programming Language :: Python :: 3.11
Requires-Dist: numpy (>=1.24.2,<2.0.0)
Requires-Dist: opencv-python-headless (>=4.7.0.68,<5.0.0.0)
Requires-Dist: pdfminer.six (>=20220524,<20220525)
Requires-Dist: pillow (>=9.4.0,<10.0.0)
Requires-Dist: tabula-py (>=2.5.1,<3.0.0)
Project-URL: Repository, https://github.com/Den4200/tungsten
